{"type": "Feature", "id": 12517944, "geometry": {"type": "Point", "coordinates": [120.000099, 26.2255]}, "properties": {"woe:id": 12517944, "woe:parent_id": 28760734, "woe:name": "\u5abd\u7956\u5834", "woe:placetype": 14, "woe:placetype_name": "Airport", "woe:lang": "CHI", "iso:country": "TW", "meta:provider": ["geoplanet:7.3.1", "geoplanet:7.3.2", "geoplanet:7.4.0", "geoplanet:7.4.1", "geoplanet:7.5.1", "geoplanet:7.5.2", "geoplanet:7.6.0", "geoplanet:7.8.1", "geoplanet:7.9.0", "geoplanet:7.10.0", "geoplanet:8.0.0", "woeplanet:8.0.0"], "meta:indexed": "2020-08-20T20:28:20.079307", "woe:alias_ENG_V": ["Matsu Airport"], "meta:updated": "2020-10-14T11:35:33.287101", "woe:alias_ENG_P": ["Ma Tsu Airport"], "woe:hierarchy": {"continent": 24865671, "country": 23424971, "town": 0, "planet": 1, "county": 0, "suburb": 0, "state": 28760734, "region": 0, "localadmin": 0}, "woe:timezone_id": 28350857, "woe:hash": "wstm4wjqsgx1", "woe:centroid": [120.000099, 26.2255], "geom:latitude": 26.2255, "geom:longitude": 120.000099, "geom:hash": "wstm4wjqsgx1", "woe:latitude": 26.2255, "geom:centroid": [120.000099, 26.2255], "woe:longitude": 120.000099, "woe:repo": "woeplanet-airport-tw", "geom:area": 0.0, "woe:scale": 19}}